setup.py
icons/coffee.svg
icons/stopwatch.svg
pomodoro_indicator/__init__.py
pomodoro_indicator/pomodoro_indicator.py
pomodoro_indicator.egg-info/PKG-INFO
pomodoro_indicator.egg-info/SOURCES.txt
pomodoro_indicator.egg-info/dependency_links.txt
pomodoro_indicator.egg-info/entry_points.txt
pomodoro_indicator.egg-info/top_level.txt