Metadata-Version: 1.1
Name: pomodoro-indicator
Version: 0.1.2
Summary: Pomodoro timer indicator.
Home-page: https://github.com/abo-abo/gtk-pomodoro-indicator
Author: Oleh Krehel
Author-email: ohwoeowho@gmail.com
License: GPLv3+
Keywords: pomodoro
Platform: UNKNOWN
Classifier: Development Status :: 4 - Beta
Classifier: Intended Audience :: End Users/Desktop
Classifier: Environment :: X11 Applications
Classifier: License :: OSI Approved :: GNU General Public License v3 or later (GPLv3+)
Classifier: Programming Language :: Python :: 2
Classifier: Programming Language :: Python :: 2.7
Classifier: Programming Language :: Python :: 3
Classifier: Programming Language :: Python :: 3.3
Classifier: Programming Language :: Python :: 3.4
Classifier: Programming Language :: Python :: 3.5
